certbot_dns_cpanel/__init__.py
certbot_dns_cpanel/dns_cpanel.py
certbot_dns_cpanel-0.4.0.dist-info/LICENSE
certbot_dns_cpanel-0.4.0.dist-info/METADATA
certbot_dns_cpanel-0.4.0.dist-info/WHEEL
certbot_dns_cpanel-0.4.0.dist-info/entry_points.txt
certbot_dns_cpanel-0.4.0.dist-info/top_level.txt
certbot_dns_cpanel-0.4.0.dist-info/RECORD
