Metadata-Version: 2.1
Name: certbot-dns-cpanel
Version: 0.4.0
Summary: certbot plugin to allow acme dns-01 authentication & installation of a name managed in cPanel.
Home-page: https://github.com/badjware/certbot-dns-cpanel
Author: Massaki Archambault
Author-email: badjware@massaki.ca
License: Apache Licence 2.0
Keywords: certbot letsencrypt cpanel dns-01 plugin
Platform: UNKNOWN
Classifier: Development Status :: 3 - Alpha
Classifier: Environment :: Plugins
Classifier: Intended Audience :: System Administrators
Classifier: License :: OSI Approved :: Apache Software License
Classifier: Operating System :: POSIX :: Linux
Classifier: Programming Language :: Python
Classifier: Topic :: Internet :: WWW/HTTP
Classifier: Topic :: Security
Classifier: Topic :: System :: Installation/Setup
Classifier: Topic :: System :: Networking
Classifier: Topic :: System :: Systems Administration
Classifier: Topic :: Utilities
License-File: LICENSE
Requires-Dist: certbot
Requires-Dist: zope.interface
